pystitcher/__init__.py
pystitcher/bookmark.py
pystitcher/skeleton.py
pystitcher/stitcher.py
pystitcher-1.0.4.dist-info/AUTHORS.rst
pystitcher-1.0.4.dist-info/LICENSE.txt
pystitcher-1.0.4.dist-info/METADATA
pystitcher-1.0.4.dist-info/WHEEL
pystitcher-1.0.4.dist-info/entry_points.txt
pystitcher-1.0.4.dist-info/top_level.txt
pystitcher-1.0.4.dist-info/RECORD
