Metadata-Version: 2.1
Name: pystitcher
Version: 1.0.4
Summary: Stitch together a PDF file from multiple sources in a declarative manner
Home-page: https://github.com/captn3m0/pystitcher
Author: Nemo
Author-email: python@captnemo.in
License: MIT
Project-URL: Documentation, https://github.com/captn3m0/pystitcher/wiki
Project-URL: Source, https://github.com/captn3m0/pystitcher
Project-URL: Changelog, https://github.com/captn3m0/pystitcher/blob/main/CHANGELOG.md
Project-URL: Tracker, https://github.com/captn3m0/pystitcher/issues
Platform: any
Classifier: Development Status :: 4 - Beta
Classifier: Programming Language :: Python
Requires-Python: >=3.7
License-File: LICENSE.txt
License-File: AUTHORS.rst
Requires-Dist: PyPDF3 (>=1.0.4)
Requires-Dist: Markdown (>=3.3.4)
Requires-Dist: html5lib (>=1.1)
Requires-Dist: validators (>=0.18.1)
Requires-Dist: importlib-metadata ; python_version < "3.8"
Provides-Extra: testing
Requires-Dist: setuptools ; extra == 'testing'
Requires-Dist: pytest ; extra == 'testing'
Requires-Dist: pytest-cov ; extra == 'testing'
